yxs_pytecio.py
yxs_pytecio-1.0.1.dist-info/METADATA
yxs_pytecio-1.0.1.dist-info/WHEEL
yxs_pytecio-1.0.1.dist-info/top_level.txt
yxs_pytecio-1.0.1.dist-info/RECORD
