Metadata-Version: 2.1
Name: yxs-pytecio
Version: 1.0.1
Summary: tecio wrapper for python
Home-page: https://github.com/blacksong/pytecio
Author: blacksong
Author-email: blacksong@yeah.net
License: UNKNOWN
Platform: any
Classifier: Programming Language :: Python :: 3
Classifier: Operating System :: OS Independent
Classifier: Topic :: Software Development :: Libraries :: Python Modules
